{
  "_id": "page.respond-landing-page",
  "_type": "page.content",
  "body": "Note: refer to cop5a lead in to being served.\r\n\r\nThe Court of Protection makes decisions financial or welfare matters for people who can’t make decisions at the time they need to be made (they ‘lack mental capacity’). \r\n\r\nThe court will decide whether someone has the mental capacity to make a particular decision for themselves, and appoint deputies to make ongoing decisions for people who lack mental capacity.\r\n\r\nA deputy is someone who makes decisions on someone's behalf if they lack capacity.\r\n\r\nDeputies are supervised but the Office of the Public Guardian (OPG).\r\n\r\n### What you need to do\r\n\r\nUse this form to tell the Court of Protection whether you agree or disagree with a property and financial affairs application.\r\n\r\n[respond-deputy.application.service.justice.gov.uk](respond-deputy.application.service.justice.gov.uk)\r\n\r\nIt usually takes about 5 minutes.\r\n\r\nYou have 14 days from the day you were told about the application to complete this form.\r\n\r\nIf you can't complete form online, or you need more time to respond you can complete the paper form:\r\n\r\n[gov.uk/government/publications/apply-to-be-part-of-court-of-protection-proceedings-form-cop5](https://www.gov.uk/government/publications/apply-to-be-part-of-court-of-protection-proceedings-form-cop5)\r\n\r\nRead about how deputies [make decisions for someone who lacks capacity](https://www.gov.uk/become-deputy).\r\n\r\nIf you need legal advice please contact a solicitor or your local Citizens Advice.\r\n\r\nAnd post it to:\r\n\r\nCourt of Protection. \r\nPO Box 70185. \r\nFirst Avenue House\r\n42-49 High Holborn\r\nLondon\r\nWC1A 9JA",
  "heading": "How to respond to a property and financial affairs application",
  "url": "respond-landing-page"
}